jsweb/__init__.py
jsweb/app.py
jsweb/auth.py
jsweb/blueprints.py
jsweb/cli.py
jsweb/database.py
jsweb/forms.py
jsweb/logging_config.py
jsweb/middleware.py
jsweb/request.py
jsweb/response.py
jsweb/routing.py
jsweb/security.py
jsweb/server.py
jsweb/static.py
jsweb/template.py
jsweb/utils.py
jsweb/validators.py
jsweb/admin/__init__.py
jsweb/admin/views.py
jsweb/admin/static/admin.css
jsweb/admin/static/jsweb_logo.png
jsweb/admin/templates/base.html
jsweb/admin/templates/dashboard.html
jsweb/admin/templates/form.html
jsweb/admin/templates/list.html
jsweb/admin/templates/login.html
jsweb/docs/__init__.py
jsweb/docs/auto_validation.py
jsweb/docs/decorators.py
jsweb/docs/introspection.py
jsweb/docs/registry.py
jsweb/docs/schema_builder.py
jsweb/docs/setup.py
jsweb/docs/ui_handlers.py
jsweb/docs/validation_middleware.py
jsweb/dto/__init__.py
jsweb/dto/core.py
jsweb/dto/decorators.py
jsweb/dto/models.py
jsweb/dto/validators.py
jsweb/project_templates/app.py.jinja
jsweb/project_templates/auth.py.jinja
jsweb/project_templates/config.py.jinja
jsweb/project_templates/forms.py.jinja
jsweb/project_templates/models.py.jinja
jsweb/project_templates/views.py.jinja
jsweb/project_templates/alembic/config.ini
jsweb/project_templates/alembic/env.py
jsweb/project_templates/alembic/script.py.mako
jsweb/static/global.css
jsweb/static/jsweb-main-logo.png
jsweb/static/jsweb.js
jsweb/static/jsweb_logo.png
jsweb/static/jsweb_logo_bg.png
jsweb/templates/_form_helpers.html
jsweb/templates/login.html
jsweb/templates/profile.html
jsweb/templates/register.html
jsweb/templates/starter_template.html
jsweb-1.2.1.dist-info/licenses/LICENSE
jsweb-1.2.1.dist-info/METADATA
jsweb-1.2.1.dist-info/WHEEL
jsweb-1.2.1.dist-info/entry_points.txt
jsweb-1.2.1.dist-info/top_level.txt
jsweb-1.2.1.dist-info/RECORD
