Metadata-Version: 2.4
Name: jsweb
Version: 1.2.1
Summary: JsWeb - A lightweight and modern Python web framework designed for speed and simplicity.
Author-email: Jones Peter <jonespetersoftware@gmail.com>
License: MIT
Project-URL: Documentation, https://jsweb-framework.site/
Project-URL: Homepage, https://github.com/Jones-peter/jsweb
Project-URL: Bug Tracker, https://github.com/Jones-peter/jsweb/issues
Keywords: JsWeb,Framework,Web,Python,ASGI,Web Server,ORM,Database,Routing,Authentication,Forms,CLI,Admin
Classifier: Development Status :: 4 - Beta
Classifier: Intended Audience :: Developers
Classifier: License :: OSI Approved :: MIT License
Classifier: Operating System :: OS Independent
Classifier: Programming Language :: Python :: 3
Classifier: Programming Language :: Python :: 3.8
Classifier: Programming Language :: Python :: 3.9
Classifier: Programming Language :: Python :: 3.10
Classifier: Programming Language :: Python :: 3.11
Classifier: Programming Language :: Python :: 3.12
Classifier: Topic :: Internet :: WWW/HTTP :: Dynamic Content
Classifier: Topic :: Software Development :: Libraries :: Application Frameworks
Requires-Python: >=3.8
License-File: LICENSE
Requires-Dist: jinja2
Requires-Dist: sqlalchemy
Requires-Dist: werkzeug
Requires-Dist: itsdangerous
Requires-Dist: alembic
Requires-Dist: markupsafe
Requires-Dist: uvicorn
Requires-Dist: pydantic<3.0,>=2.0
Provides-Extra: dev
Requires-Dist: watchdog>=3.0; extra == "dev"
Requires-Dist: websockets>=11.0; extra == "dev"
Requires-Dist: pytest>=7.4; extra == "dev"
Requires-Dist: pytest-cov>=4.1; extra == "dev"
Requires-Dist: pytest-asyncio>=0.21; extra == "dev"
Requires-Dist: black>=24.0; extra == "dev"
Requires-Dist: isort>=5.12; extra == "dev"
Requires-Dist: flake8>=7.0; extra == "dev"
Requires-Dist: flake8-bugbear>=23.0; extra == "dev"
Requires-Dist: flake8-comprehensions>=3.14; extra == "dev"
Requires-Dist: mypy>=1.7; extra == "dev"
Requires-Dist: bandit>=1.7; extra == "dev"
Requires-Dist: safety>=2.3; extra == "dev"
Requires-Dist: pre-commit>=3.5; extra == "dev"
Provides-Extra: qr
Requires-Dist: qrcode[pil]; extra == "qr"
Provides-Extra: postgresql
Requires-Dist: psycopg2-binary; extra == "postgresql"
Dynamic: license-file
